aiidalab_qe_vibroscopy/__init__.py
aiidalab_qe_vibroscopy/__main__.py
aiidalab_qe_vibroscopy/app/__init__.py
aiidalab_qe_vibroscopy/app/result.py
aiidalab_qe_vibroscopy/app/settings.py
aiidalab_qe_vibroscopy/app/workchain.py
aiidalab_qe_vibroscopy/utils/dielectric/result.py
aiidalab_qe_vibroscopy/utils/euphonic/Detached_app.ipynb
aiidalab_qe_vibroscopy/utils/euphonic/__init__.py
aiidalab_qe_vibroscopy/utils/euphonic/bands_pdos.py
aiidalab_qe_vibroscopy/utils/euphonic/euphonic_base_widgets.py
aiidalab_qe_vibroscopy/utils/euphonic/euphonic_powder_widgets.py
aiidalab_qe_vibroscopy/utils/euphonic/euphonic_q_planes_widgets.py
aiidalab_qe_vibroscopy/utils/euphonic/euphonic_single_crystal_widgets.py
aiidalab_qe_vibroscopy/utils/euphonic/intensity_maps.py
aiidalab_qe_vibroscopy/utils/euphonic/static/style.css
aiidalab_qe_vibroscopy/utils/euphonic/static/welcome.jinja
aiidalab_qe_vibroscopy/utils/phonons/result.py
aiidalab_qe_vibroscopy/utils/raman/result.py
aiidalab_qe_vibroscopy/workflows/vibroworkchain.py
aiidalab_qe_vibroscopy-1.1.4.dist-info/entry_points.txt
aiidalab_qe_vibroscopy-1.1.4.dist-info/LICENSE.txt
aiidalab_qe_vibroscopy-1.1.4.dist-info/WHEEL
aiidalab_qe_vibroscopy-1.1.4.dist-info/METADATA
aiidalab_qe_vibroscopy-1.1.4.dist-info/RECORD
