Metadata-Version: 2.1
Name: aiidalab-qe-vibroscopy
Version: 1.1.4
Summary: AiiDAlab QE plugin for vibrational spectoscopies.
Keywords: aiidalab,plugin
Author-email: Miki Bonacci <miki.bonacci@psi.ch>, Andres Ortega Guerrero <andres.ortega-guerrero@empa.ch>
Requires-Python: >=3.8
Classifier: Development Status :: 5 - Production/Stable
Requires-Dist: aiida-vibroscopy>=1.0.2
Requires-Dist: aiida-phonopy>=1.1.3
Requires-Dist: phonopy
Requires-Dist: pre-commit
Requires-Dist: euphonic
Requires-Dist: kaleido
Requires-Dist: weas-widget==0.1.12
Project-URL: Source, https://github.com/mikibonacci/aiidalab-qe-vibroscopy
